overlay/__init__.py
overlay/window.py
overlay/template/__init__.py
overlay/template/asset_finder.py
overlay/template/futuristic.py
overlay/template/prefab.py
overlay/template/ui/futuristic/TextWindow.png
overlay-1.1.5.dist-info/LICENSE
overlay-1.1.5.dist-info/METADATA
overlay-1.1.5.dist-info/WHEEL
overlay-1.1.5.dist-info/top_level.txt
overlay-1.1.5.dist-info/RECORD
