Metadata-Version: 2.1
Name: overlay
Version: 1.1.5
Summary: A package that creates and manipulates screen overlays based on tkinter.
Home-page: https://github.com/davidmaamoaix/Overlay
Author: David Ma
Author-email: davidma@davidma.cn
License: MIT
Platform: UNKNOWN
